rossby/__init__.py
rossby/api_config.py
rossby/default_response.py
rossby/rossby.py
tests/__init__.py
tests/base_test.py
tests/special.py
rossby-0.0.3.dist-info/LICENSE
rossby-0.0.3.dist-info/METADATA
rossby-0.0.3.dist-info/WHEEL
rossby-0.0.3.dist-info/top_level.txt
rossby-0.0.3.dist-info/RECORD
