Metadata-Version: 2.1
Name: rossby
Version: 0.0.3
Summary: A wrapper for the U.S. National Weather Service API
Home-page: https://github.com/nat5142/rossby
Author: Nicholas Tulli
Author-email: nat5142@psu.edu
License: UNKNOWN
Keywords: national weather service nws noaa api wrapper
Platform: UNKNOWN
Classifier: Programming Language :: Python :: 3
Classifier: License :: OSI Approved :: MIT License
Classifier: Operating System :: OS Independent
Requires-Python: >=3.6
Requires-Dist: requests (>=2.20)
Requires-Dist: addict (==2.2.0)
